[{"url":"/public/cars/e66a165e5ee3f80688283c55b3cfabbb.jpg","revision":"e66a165e5ee3f80688283c55b3cfabbb.jpgSun Nov 26 2023 12:31:26 GMT+0300 (East Africa Time)"},{"url":"/public/cars/pickup-types.jpg","revision":"pickup-types.jpgSun Nov 26 2023 12:31:26 GMT+0300 (East Africa Time)"},{"url":"/public/cars/realistic-car-sedan-front-view-side-view-back-view_210962-78.png","revision":"realistic-car-sedan-front-view-side-view-back-view_210962-78.pngSun Nov 26 2023 12:31:26 GMT+0300 (East Africa Time)"},{"url":"/public/cars/sedan-back.png","revision":"sedan-back.pngSun Nov 26 2023 12:31:26 GMT+0300 (East Africa Time)"},{"url":"/public/cars/sedan-front.png","revision":"sedan-front.pngSun Nov 26 2023 12:31:26 GMT+0300 (East Africa Time)"},{"url":"/public/cars/sedan-full-outline.png","revision":"sedan-full-outline.pngSun Nov 26 2023 12:31:26 GMT+0300 (East Africa Time)"},{"url":"/public/cars/sedan-full-outline2.png","revision":"sedan-full-outline2.pngSun Nov 26 2023 12:31:26 GMT+0300 (East Africa Time)"},{"url":"/public/cars/sedan-side.png","revision":"sedan-side.pngSun Nov 26 2023 12:31:26 GMT+0300 (East Africa Time)"},{"url":"/public/cars/volkswagen-golf-variant-1995.jpg","revision":"volkswagen-golf-variant-1995.jpgSun Nov 26 2023 12:31:26 GMT+0300 (East Africa Time)"},{"url":"/public/cars/volkswagen-touareg-r50-2009.jpg","revision":"volkswagen-touareg-r50-2009.jpgSun Nov 26 2023 12:31:26 GMT+0300 (East Africa Time)"},{"url":"/public/fonts/licensePlate2.otf","revision":"licensePlate2.otfSun Nov 26 2023 12:31:26 GMT+0300 (East Africa Time)"},{"url":"/public/fonts/licensePlate2.ttf","revision":"licensePlate2.ttfSun Nov 26 2023 12:31:26 GMT+0300 (East Africa Time)"},{"url":"/public/images/10660-200.png","revision":"10660-200.pngSun Nov 26 2023 12:31:26 GMT+0300 (East Africa Time)"},{"url":"/public/images/account.svg","revision":"account.svgSun Nov 26 2023 12:31:26 GMT+0300 (East Africa Time)"},{"url":"/public/images/accountgroup.svg","revision":"accountgroup.svgSun Nov 26 2023 12:31:26 GMT+0300 (East Africa Time)"},{"url":"/public/images/add-rect.svg","revision":"add-rect.svgSun Nov 26 2023 12:31:26 GMT+0300 (East Africa Time)"},{"url":"/public/images/add.svg","revision":"add.svgSun Nov 26 2023 12:31:26 GMT+0300 (East Africa Time)"},{"url":"/public/images/agent.png","revision":"agent.pngSun Nov 26 2023 12:31:26 GMT+0300 (East Africa Time)"},{"url":"/public/images/agent.webp","revision":"agent.webpSun Nov 26 2023 12:31:26 GMT+0300 (East Africa Time)"},{"url":"/public/images/american.svg","revision":"american.svgSun Nov 26 2023 12:31:26 GMT+0300 (East Africa Time)"},{"url":"/public/images/animat-wrench.gif","revision":"animat-wrench.gifSun Nov 26 2023 12:31:26 GMT+0300 (East Africa Time)"},{"url":"/public/images/appliance.png","revision":"appliance.pngSun Nov 26 2023 12:31:26 GMT+0300 (East Africa Time)"},{"url":"/public/images/appliance.svg","revision":"appliance.svgSun Nov 26 2023 12:31:26 GMT+0300 (East Africa Time)"},{"url":"/public/images/appointment.png","revision":"appointment.pngSun Nov 26 2023 12:31:26 GMT+0300 (East Africa Time)"},{"url":"/public/images/approved-profile.svg","revision":"approved-profile.svgSun Nov 26 2023 12:31:26 GMT+0300 (East Africa Time)"},{"url":"/public/images/archive.svg","revision":"archive.svgSun Nov 26 2023 12:31:26 GMT+0300 (East Africa Time)"},{"url":"/public/images/arrowback.svg","revision":"arrowback.svgSun Nov 26 2023 12:31:26 GMT+0300 (East Africa Time)"},{"url":"/public/images/arrowdobledown.svg","revision":"arrowdobledown.svgSun Nov 26 2023 12:31:26 GMT+0300 (East Africa Time)"},{"url":"/public/images/arrowdoubleup.svg","revision":"arrowdoubleup.svgSun Nov 26 2023 12:31:26 GMT+0300 (East Africa Time)"},{"url":"/public/images/arrowdown.svg","revision":"arrowdown.svgSun Nov 26 2023 12:31:26 GMT+0300 (East Africa Time)"},{"url":"/public/images/arrowforward.svg","revision":"arrowforward.svgSun Nov 26 2023 12:31:26 GMT+0300 (East Africa Time)"},{"url":"/public/images/arrowright.png","revision":"arrowright.pngSun Nov 26 2023 12:31:26 GMT+0300 (East Africa Time)"},{"url":"/public/images/calculate.svg","revision":"calculate.svgSun Nov 26 2023 12:31:26 GMT+0300 (East Africa Time)"},{"url":"/public/images/call.svg","revision":"call.svgSun Nov 26 2023 12:31:26 GMT+0300 (East Africa Time)"},{"url":"/public/images/camera.svg","revision":"camera.svgSun Nov 26 2023 12:31:26 GMT+0300 (East Africa Time)"},{"url":"/public/images/car1.jpg","revision":"car1.jpgSun Nov 26 2023 12:31:26 GMT+0300 (East Africa Time)"},{"url":"/public/images/car2.jpg","revision":"car2.jpgSun Nov 26 2023 12:31:26 GMT+0300 (East Africa Time)"},{"url":"/public/images/car3.jpg","revision":"car3.jpgSun Nov 26 2023 12:31:26 GMT+0300 (East Africa Time)"},{"url":"/public/images/car4.jpg","revision":"car4.jpgSun Nov 26 2023 12:31:26 GMT+0300 (East Africa Time)"},{"url":"/public/images/car5.jpg","revision":"car5.jpgSun Nov 26 2023 12:31:26 GMT+0300 (East Africa Time)"},{"url":"/public/images/car6.jpg","revision":"car6.jpgSun Nov 26 2023 12:31:26 GMT+0300 (East Africa Time)"},{"url":"/public/images/caricon.svg","revision":"caricon.svgSun Nov 26 2023 12:31:26 GMT+0300 (East Africa Time)"},{"url":"/public/images/carin1.jpg","revision":"carin1.jpgSun Nov 26 2023 12:31:26 GMT+0300 (East Africa Time)"},{"url":"/public/images/cars.png","revision":"cars.pngSun Nov 26 2023 12:31:26 GMT+0300 (East Africa Time)"},{"url":"/public/images/cars2.png","revision":"cars2.pngSun Nov 26 2023 12:31:26 GMT+0300 (East Africa Time)"},{"url":"/public/images/cert3yaredbekuru2.crt","revision":"cert3yaredbekuru2.crtSun Nov 26 2023 12:31:26 GMT+0300 (East Africa Time)"},{"url":"/public/images/certificate.svg","revision":"certificate.svgSun Nov 26 2023 12:31:26 GMT+0300 (East Africa Time)"},{"url":"/public/images/certificate1.svg","revision":"certificate1.svgSun Nov 26 2023 12:31:26 GMT+0300 (East Africa Time)"},{"url":"/public/images/check.png","revision":"check.pngSun Nov 26 2023 12:31:26 GMT+0300 (East Africa Time)"},{"url":"/public/images/check.webp","revision":"check.webpSun Nov 26 2023 12:31:26 GMT+0300 (East Africa Time)"},{"url":"/public/images/checkbox-checked.svg","revision":"checkbox-checked.svgSun Nov 26 2023 12:31:26 GMT+0300 (East Africa Time)"},{"url":"/public/images/checkbox-unchecked.svg","revision":"checkbox-unchecked.svgSun Nov 26 2023 12:31:26 GMT+0300 (East Africa Time)"},{"url":"/public/images/clients.png","revision":"clients.pngSun Nov 26 2023 12:31:26 GMT+0300 (East Africa Time)"},{"url":"/public/images/close-circle.svg","revision":"close-circle.svgSun Nov 26 2023 12:31:26 GMT+0300 (East Africa Time)"},{"url":"/public/images/close-rect.svg","revision":"close-rect.svgSun Nov 26 2023 12:31:26 GMT+0300 (East Africa Time)"},{"url":"/public/images/close.svg","revision":"close.svgSun Nov 26 2023 12:31:26 GMT+0300 (East Africa Time)"},{"url":"/public/images/code.svg","revision":"code.svgSun Nov 26 2023 12:31:26 GMT+0300 (East Africa Time)"},{"url":"/public/images/company.png","revision":"company.pngSun Nov 26 2023 12:31:26 GMT+0300 (East Africa Time)"},{"url":"/public/images/contact.jpg","revision":"contact.jpgSun Nov 26 2023 12:31:26 GMT+0300 (East Africa Time)"},{"url":"/public/images/contact.svg","revision":"contact.svgSun Nov 26 2023 12:31:26 GMT+0300 (East Africa Time)"},{"url":"/public/images/Daniel Garage v1.0.mhtml","revision":"Daniel Garage v1.0.mhtmlSun Nov 26 2023 12:31:26 GMT+0300 (East Africa Time)"},{"url":"/public/images/date.png","revision":"date.pngSun Nov 26 2023 12:31:26 GMT+0300 (East Africa Time)"},{"url":"/public/images/delete.svg","revision":"delete.svgSun Nov 26 2023 12:31:26 GMT+0300 (East Africa Time)"},{"url":"/public/images/doc.svg","revision":"doc.svgSun Nov 26 2023 12:31:26 GMT+0300 (East Africa Time)"},{"url":"/public/images/doneall.svg","revision":"doneall.svgSun Nov 26 2023 12:31:26 GMT+0300 (East Africa Time)"},{"url":"/public/images/download.svg","revision":"download.svgSun Nov 26 2023 12:31:26 GMT+0300 (East Africa Time)"},{"url":"/public/images/drill.svg","revision":"drill.svgSun Nov 26 2023 12:31:26 GMT+0300 (East Africa Time)"},{"url":"/public/images/duotone-cross-square-svgrepo-com.svg","revision":"duotone-cross-square-svgrepo-com.svgSun Nov 26 2023 12:31:26 GMT+0300 (East Africa Time)"},{"url":"/public/images/edit.svg","revision":"edit.svgSun Nov 26 2023 12:31:26 GMT+0300 (East Africa Time)"},{"url":"/public/images/experiment.svg","revision":"experiment.svgSun Nov 26 2023 12:31:26 GMT+0300 (East Africa Time)"},{"url":"/public/images/favicon.png","revision":"favicon.pngSun Nov 26 2023 12:31:26 GMT+0300 (East Africa Time)"},{"url":"/public/images/favicon2.png","revision":"favicon2.pngSun Nov 26 2023 12:31:26 GMT+0300 (East Africa Time)"},{"url":"/public/images/flat.svg","revision":"flat.svgSun Nov 26 2023 12:31:26 GMT+0300 (East Africa Time)"},{"url":"/public/images/genderM.png","revision":"genderM.pngSun Nov 26 2023 12:31:26 GMT+0300 (East Africa Time)"},{"url":"/public/images/Hashtag.svg","revision":"Hashtag.svgSun Nov 26 2023 12:31:26 GMT+0300 (East Africa Time)"},{"url":"/public/images/history.svg","revision":"history.svgSun Nov 26 2023 12:31:26 GMT+0300 (East Africa Time)"},{"url":"/public/images/home.svg","revision":"home.svgSun Nov 26 2023 12:31:26 GMT+0300 (East Africa Time)"},{"url":"/public/images/info.png","revision":"info.pngSun Nov 26 2023 12:31:26 GMT+0300 (East Africa Time)"},{"url":"/public/images/Inspection.png","revision":"Inspection.pngSun Nov 26 2023 12:31:26 GMT+0300 (East Africa Time)"},{"url":"/public/images/link_1.svg","revision":"link_1.svgSun Nov 26 2023 12:31:26 GMT+0300 (East Africa Time)"},{"url":"/public/images/list.png","revision":"list.pngSun Nov 26 2023 12:31:26 GMT+0300 (East Africa Time)"},{"url":"/public/images/loc.jpg","revision":"loc.jpgSun Nov 26 2023 12:31:26 GMT+0300 (East Africa Time)"},{"url":"/public/images/location.svg","revision":"location.svgSun Nov 26 2023 12:31:26 GMT+0300 (East Africa Time)"},{"url":"/public/images/log-in.svg","revision":"log-in.svgSun Nov 26 2023 12:31:26 GMT+0300 (East Africa Time)"},{"url":"/public/images/mic.svg","revision":"mic.svgSun Nov 26 2023 12:31:26 GMT+0300 (East Africa Time)"},{"url":"/public/images/mic_FILL.svg","revision":"mic_FILL.svgSun Nov 26 2023 12:31:26 GMT+0300 (East Africa Time)"},{"url":"/public/images/new (2).webp","revision":"new (2).webpSun Nov 26 2023 12:31:26 GMT+0300 (East Africa Time)"},{"url":"/public/images/newpic.svg","revision":"newpic.svgSun Nov 26 2023 12:31:26 GMT+0300 (East Africa Time)"},{"url":"/public/images/notification.svg","revision":"notification.svgSun Nov 26 2023 12:31:26 GMT+0300 (East Africa Time)"},{"url":"/public/images/offline.svg","revision":"offline.svgSun Nov 26 2023 12:31:26 GMT+0300 (East Africa Time)"},{"url":"/public/images/open_in_new.svg","revision":"open_in_new.svgSun Nov 26 2023 12:31:26 GMT+0300 (East Africa Time)"},{"url":"/public/images/parts.svg","revision":"parts.svgSun Nov 26 2023 12:31:26 GMT+0300 (East Africa Time)"},{"url":"/public/images/password.svg","revision":"password.svgSun Nov 26 2023 12:31:26 GMT+0300 (East Africa Time)"},{"url":"/public/images/pending.svg","revision":"pending.svgSun Nov 26 2023 12:31:26 GMT+0300 (East Africa Time)"},{"url":"/public/images/person2.png","revision":"person2.pngSun Nov 26 2023 12:31:26 GMT+0300 (East Africa Time)"},{"url":"/public/images/phone (2).png","revision":"phone (2).pngSun Nov 26 2023 12:31:26 GMT+0300 (East Africa Time)"},{"url":"/public/images/phone.jpg","revision":"phone.jpgSun Nov 26 2023 12:31:26 GMT+0300 (East Africa Time)"},{"url":"/public/images/phone.png","revision":"phone.pngSun Nov 26 2023 12:31:26 GMT+0300 (East Africa Time)"},{"url":"/public/images/phone.svg","revision":"phone.svgSun Nov 26 2023 12:31:26 GMT+0300 (East Africa Time)"},{"url":"/public/images/plier.svg","revision":"plier.svgSun Nov 26 2023 12:31:26 GMT+0300 (East Africa Time)"},{"url":"/public/images/plus.svg","revision":"plus.svgSun Nov 26 2023 12:31:26 GMT+0300 (East Africa Time)"},{"url":"/public/images/print.svg","revision":"print.svgSun Nov 26 2023 12:31:26 GMT+0300 (East Africa Time)"},{"url":"/public/images/printlock.svg","revision":"printlock.svgSun Nov 26 2023 12:31:26 GMT+0300 (East Africa Time)"},{"url":"/public/images/qr_code.svg","revision":"qr_code.svgSun Nov 26 2023 12:31:26 GMT+0300 (East Africa Time)"},{"url":"/public/images/R.png","revision":"R.pngSun Nov 26 2023 12:31:26 GMT+0300 (East Africa Time)"},{"url":"/public/images/radio_button_checked.svg","revision":"radio_button_checked.svgSun Nov 26 2023 12:31:26 GMT+0300 (East Africa Time)"},{"url":"/public/images/radio_button_unchecked.svg","revision":"radio_button_unchecked.svgSun Nov 26 2023 12:31:26 GMT+0300 (East Africa Time)"},{"url":"/public/images/recyclebin.png","revision":"recyclebin.pngSun Nov 26 2023 12:31:26 GMT+0300 (East Africa Time)"},{"url":"/public/images/recyclebin.webp","revision":"recyclebin.webpSun Nov 26 2023 12:31:26 GMT+0300 (East Africa Time)"},{"url":"/public/images/refresh.svg","revision":"refresh.svgSun Nov 26 2023 12:31:26 GMT+0300 (East Africa Time)"},{"url":"/public/images/repair.png","revision":"repair.pngSun Nov 26 2023 12:31:26 GMT+0300 (East Africa Time)"},{"url":"/public/images/report.png","revision":"report.pngSun Nov 26 2023 12:31:26 GMT+0300 (East Africa Time)"},{"url":"/public/images/schedule.svg","revision":"schedule.svgSun Nov 26 2023 12:31:26 GMT+0300 (East Africa Time)"},{"url":"/public/images/search.png","revision":"search.pngSun Nov 26 2023 12:31:26 GMT+0300 (East Africa Time)"},{"url":"/public/images/search.svg","revision":"search.svgSun Nov 26 2023 12:31:26 GMT+0300 (East Africa Time)"},{"url":"/public/images/settings.svg","revision":"settings.svgSun Nov 26 2023 12:31:26 GMT+0300 (East Africa Time)"},{"url":"/public/images/spanner.svg","revision":"spanner.svgSun Nov 26 2023 12:31:26 GMT+0300 (East Africa Time)"},{"url":"/public/images/status.svg","revision":"status.svgSun Nov 26 2023 12:31:26 GMT+0300 (East Africa Time)"},{"url":"/public/images/stock.png","revision":"stock.pngSun Nov 26 2023 12:31:26 GMT+0300 (East Africa Time)"},{"url":"/public/images/stock1.jpg","revision":"stock1.jpgSun Nov 26 2023 12:31:26 GMT+0300 (East Africa Time)"},{"url":"/public/images/stock2.jpg","revision":"stock2.jpgSun Nov 26 2023 12:31:26 GMT+0300 (East Africa Time)"},{"url":"/public/images/stock2.png","revision":"stock2.pngSun Nov 26 2023 12:31:26 GMT+0300 (East Africa Time)"},{"url":"/public/images/stop_circle.svg","revision":"stop_circle.svgSun Nov 26 2023 12:31:26 GMT+0300 (East Africa Time)"},{"url":"/public/images/sync.webp","revision":"sync.webpSun Nov 26 2023 12:31:26 GMT+0300 (East Africa Time)"},{"url":"/public/images/target.svg","revision":"target.svgSun Nov 26 2023 12:31:26 GMT+0300 (East Africa Time)"},{"url":"/public/images/technician.png","revision":"technician.pngSun Nov 26 2023 12:31:26 GMT+0300 (East Africa Time)"},{"url":"/public/images/toggle_off.svg","revision":"toggle_off.svgSun Nov 26 2023 12:31:26 GMT+0300 (East Africa Time)"},{"url":"/public/images/toggle_on.svg","revision":"toggle_on.svgSun Nov 26 2023 12:31:26 GMT+0300 (East Africa Time)"},{"url":"/public/images/transaction.png","revision":"transaction.pngSun Nov 26 2023 12:31:26 GMT+0300 (East Africa Time)"},{"url":"/public/images/types-of-cars.webp","revision":"types-of-cars.webpSun Nov 26 2023 12:31:26 GMT+0300 (East Africa Time)"},{"url":"/public/images/unapproved-profile.svg","revision":"unapproved-profile.svgSun Nov 26 2023 12:31:26 GMT+0300 (East Africa Time)"},{"url":"/public/images/unarchive.svg","revision":"unarchive.svgSun Nov 26 2023 12:31:26 GMT+0300 (East Africa Time)"},{"url":"/public/images/unlink_1.svg","revision":"unlink_1.svgSun Nov 26 2023 12:31:26 GMT+0300 (East Africa Time)"},{"url":"/public/images/unpaid.png","revision":"unpaid.pngSun Nov 26 2023 12:31:26 GMT+0300 (East Africa Time)"},{"url":"/public/images/update.svg","revision":"update.svgSun Nov 26 2023 12:31:26 GMT+0300 (East Africa Time)"},{"url":"/public/images/upload.svg","revision":"upload.svgSun Nov 26 2023 12:31:26 GMT+0300 (East Africa Time)"},{"url":"/public/images/upload2.svg","revision":"upload2.svgSun Nov 26 2023 12:31:26 GMT+0300 (East Africa Time)"},{"url":"/public/images/verified.svg","revision":"verified.svgSun Nov 26 2023 12:31:26 GMT+0300 (East Africa Time)"},{"url":"/public/images/warning.svg","revision":"warning.svgSun Nov 26 2023 12:31:26 GMT+0300 (East Africa Time)"}]